dogwood/__init__.py
dogwood/errors.py
dogwood/model_expansion.py
dogwood/experiments/__init__.py
dogwood/experiments/model_based_transfer.py
dogwood/pretraining/__init__.py
dogwood/pretraining/imagenet_data_processor.py
dogwood/pretraining/mini_imagenet_loader.py
dogwood/pretraining/pretraining_pool.py
dogwood-0.0.8.dist-info/LICENSE
dogwood-0.0.8.dist-info/METADATA
dogwood-0.0.8.dist-info/WHEEL
dogwood-0.0.8.dist-info/top_level.txt
dogwood-0.0.8.dist-info/RECORD
