Metadata-Version: 2.1
Name: dogwood
Version: 0.0.8
Summary: Leo's PhD repository.
Home-page: https://github.com/kostaleonard/dogwood
Author: Leo Kosta
Author-email: kostaleonard@gmail.com
License: UNKNOWN
Project-URL: Bug Tracker, https://github.com/kostaleonard/dogwood/issues
Platform: UNKNOWN
Classifier: Programming Language :: Python :: 3
Classifier: License :: OSI Approved :: MIT License
Classifier: Operating System :: OS Independent
License-File: LICENSE
